py5gl/__init__.py
py5gl/engine.py
py5gl-0.1.2.dist-info/licenses/LICENSE
py5gl-0.1.2.dist-info/METADATA
py5gl-0.1.2.dist-info/WHEEL
py5gl-0.1.2.dist-info/top_level.txt
py5gl-0.1.2.dist-info/RECORD
